{
    "北京": "NA",
    "天津": "NA",
    "上海": "PM2.5",
    "重庆": "PM2.5",
    "河北": "PM10",
    "山西": "PM2.5",
    "内蒙古": "PM2.5",
    "辽宁": "NA",
    "吉林": "NA",
    "黑龙江": "PM2.5",
    "江苏": "PM2.5",
    "浙江": "PM2.5",
    "安徽": "PM2.5",
    "福建": "PM2.5",
    "江西": "PM2.5",
    "山东": "PM2.5",
    "河南": "PM2.5",
    "湖北": "PM2.5",
    "湖南": "PM2.5",
    "广东": "O3",
    "广西": "PM10",
    "海南": "O3",
    "四川": "PM2.5",
    "贵州": "PM2.5",
    "云南": "NA",
    "西藏": "O3",
    "陕西": "PM2.5",
    "甘肃": "PM2.5",
    "青海": "PM10",
    "宁夏": "PM10",
    "新疆": "PM2.5"
}